{
  "aalfm": "2026-05-19",
  "acnhl": "2026-05-20",
  "adioc": "2026-05-11",
  "adpnd": "2026-05-15",
  "agplx": "2026-05-20",
  "ahged": "2026-05-17",
  "ahnhf": "2026-05-15",
  "akcjk": "2026-05-16",
  "akjjb": "2026-05-19",
  "akmlk": "2026-05-10",
  "akmlo": "2026-05-10",
  "aldgo": "2026-05-20",
  "alghd": "2026-05-20",
  "alnbl": "2026-05-20",
  "amxbl": "2026-05-18",
  "anbgp": "2026-05-20",
  "ancel": "2026-05-20",
  "aocho": "2026-05-20",
  "aofxc": "2026-05-12",
  "apbhx": "2026-05-10",
  "apelo": "2026-05-20",
  "apodc": "2026-05-13",
  "bbbcf": "2026-05-20",
  "bbbgpj": "2026-05-20",
  "bbiim": "2026-05-20",
  "bbjxf": "2026-05-20",
  "bbpebj": "2026-05-19",
  "bbxxg": "2026-05-20",
  "bccxn": "2026-05-20",
  "bcfxkj": "2026-05-20",
  "bcgpoh": "2026-05-16",
  "bchdm": "2026-05-10",
  "bcjdg": "2026-05-20",
  "bcxmxn": "2026-05-20",
  "bdhedd": "2026-05-20",
  "bdkbxm": "2026-05-14",
  "bebcmf": "2026-05-10",
  "bedegx": "2026-05-17",
  "beegjf": "2026-05-14",
  "befjol": "2026-05-14",
  "begoxp": "2026-05-20",
  "behcbg": "2026-05-18",
  "bejoxg": "2026-05-20",
  "bekijd": "2026-05-20",
  "bekxec": "2026-05-20",
  "benhxh": "2026-05-11",
  "benjjg": "2026-05-20",
  "bennhn": "2026-05-20",
  "beokcp": "2026-05-20",
  "bepecx": "2026-05-13",
  "bepxlm": "2026-05-20",
  "bffxo": "2026-05-12",
  "bfxdd": "2026-05-13",
  "bgbbk": "2026-05-20",
  "bgidhl": "2026-05-19",
  "bgldc": "2026-05-20",
  "bgndc": "2026-05-20",
  "bgpkgj": "2026-05-20",
  "bhgne": "2026-05-20",
  "bhiifd": "2026-05-19",
  "bhkfnl": "2026-05-20",
  "bhlonj": "2026-05-16",
  "bhnbfn": "2026-05-13",
  "bhnkc": "2026-05-14",
  "bhondm": "2026-05-19",
  "bhpfxe": "2026-05-20",
  "bhpmok": "2026-05-20",
  "bibgdj": "2026-05-15",
  "bibkcl": "2026-05-20",
  "bibobf": "2026-05-10",
  "bicgfn": "2026-05-10",
  "bicjmx": "2026-05-13",
  "biedhm": "2026-05-10",
  "bihei": "2026-05-20",
  "bincke": "2026-05-10",
  "biomfl": "2026-05-20",
  "bjbddp": "2026-05-16",
  "bjdkbe": "2026-05-20",
  "bjehji": "2026-05-10",
  "bjhhj": "2026-05-19",
  "bjhknc": "2026-05-20",
  "bjhneg": "2026-05-11",
  "bjhpe": "2026-05-20",
  "bjjgkm": "2026-05-20",
  "bjjoim": "2026-05-17",
  "bjnlgg": "2026-05-14",
  "bjoblg": "2026-05-20",
  "bjxfb": "2026-05-20",
  "bjxmfd": "2026-05-20",
  "bkbkon": "2026-05-10",
  "bkbpex": "2026-05-15",
  "bkdfff": "2026-05-13",
  "bkfjgl": "2026-05-18",
  "bkhihk": "2026-05-12",
  "bkjmhg": "2026-05-15",
  "bklgnn": "2026-05-20",
  "bklxee": "2026-05-20",
  "bkncj": "2026-05-15",
  "bkodoe": "2026-05-10",
  "bkpkgm": "2026-05-12",
  "bkpllx": "2026-05-20",
  "blecj": "2026-05-10",
  "blefhc": "2026-05-20",
  "blgikh": "2026-05-20",
  "blgmec": "2026-05-20",
  "blhem": "2026-05-10",
  "blhglf": "2026-05-20",
  "blkgm": "2026-05-16",
  "blmhc": "2026-05-20",
  "blxdix": "2026-05-10",
  "bmbgl": "2026-05-10",
  "bmfci": "2026-05-20",
  "bmgenh": "2026-05-20",
  "bmmbio": "2026-05-20",
  "bmmxl": "2026-05-10",
  "bmnobk": "2026-05-20",
  "bmohfo": "2026-05-20",
  "bmomk": "2026-05-20",
  "bobobh": "2026-05-18",
  "bogfb": "2026-05-10",
  "boloxp": "2026-05-19",
  "bomnhk": "2026-05-11",
  "boomfo": "2026-05-20",
  "bpcopx": "2026-05-20",
  "bpixdm": "2026-05-14",
  "bpjnp": "2026-05-12",
  "bpnpxd": "2026-05-20",
  "bxehxe": "2026-05-10",
  "bxhxg": "2026-05-20",
  "bxiil": "2026-05-20",
  "bxkhjj": "2026-05-20",
  "bxnofd": "2026-05-20",
  "bxpkeg": "2026-05-20",
  "cbeec": "2026-05-20",
  "cbffbo": "2026-05-19",
  "cbfopm": "2026-05-20",
  "cbmbn": "2026-05-20",
  "cbndln": "2026-05-20",
  "cbodcn": "2026-05-18",
  "cbolgh": "2026-05-20",
  "cbonxk": "2026-05-13",
  "cbpbfc": "2026-05-20",
  "ccfbhe": "2026-05-18",
  "cclef": "2026-05-20",
  "ccljlb": "2026-05-20",
  "ccmfhg": "2026-05-20",
  "ccnfol": "2026-05-20",
  "ccngek": "2026-05-20",
  "ccnpjo": "2026-05-11",
  "ccnxfk": "2026-05-19",
  "ccopif": "2026-05-15",
  "ccphmf": "2026-05-10",
  "cdbipj": "2026-05-20",
  "cdbjeb": "2026-05-20",
  "cdbki": "2026-05-10",
  "cdcemm": "2026-05-10",
  "cdcpem": "2026-05-10",
  "cddond": "2026-05-20",
  "cdedpb": "2026-05-20",
  "cdfdib": "2026-05-20",
  "cdffbx": "2026-05-20",
  "cdgcg": "2026-05-12",
  "cdgxgc": "2026-05-20",
  "cdhicm": "2026-05-11",
  "cdjlji": "2026-05-20",
  "cdjnoj": "2026-05-20",
  "cdkbfm": "2026-05-18",
  "cdldkd": "2026-05-20",
  "cdmbcm": "2026-05-18",
  "cdmbme": "2026-05-16",
  "cdmjfx": "2026-05-20",
  "cdngib": "2026-05-16",
  "cdockj": "2026-05-12",
  "cdoeog": "2026-05-20",
  "cdogfc": "2026-05-18",
  "cdooem": "2026-05-20",
  "cdpkoo": "2026-05-17",
  "cdplfh": "2026-05-20",
  "cdpmgl": "2026-05-11",
  "cdpned": "2026-05-16",
  "cebepe": "2026-05-19",
  "cebodk": "2026-05-20",
  "cecbbl": "2026-05-19",
  "ceeenx": "2026-05-20",
  "ceehop": "2026-05-18",
  "ceepol": "2026-05-20",
  "ceinik": "2026-05-18",
  "cejhid": "2026-05-10",
  "cejkxg": "2026-05-10",
  "cejlh": "2026-05-20",
  "cekdnx": "2026-05-20",
  "cekekg": "2026-05-20",
  "cekhne": "2026-05-19",
  "cekjok": "2026-05-20",
  "cekpop": "2026-05-10",
  "celild": "2026-05-15",
  "cellxn": "2026-05-15",
  "celxfk": "2026-05-12",
  "cembh": "2026-05-20",
  "cemcob": "2026-05-17",
  "cemgdb": "2026-05-19",
  "cenpc": "2026-05-10",
  "ceonko": "2026-05-11",
  "cexcfp": "2026-05-10",
  "cexmxc": "2026-05-20",
  "cfdcnn": "2026-05-20",
  "cfegnf": "2026-05-20",
  "cfepel": "2026-05-20",
  "cffejn": "2026-05-17",
  "cffhc": "2026-05-12",
  "cffjfx": "2026-05-20",
  "cffkf": "2026-05-20",
  "cffxjo": "2026-05-12",
  "cfgjxn": "2026-05-20",
  "cfhkfd": "2026-05-15",
  "cfjmf": "2026-05-20",
  "cfkofn": "2026-05-17",
  "cfpnfm": "2026-05-20",
  "cfxnpf": "2026-05-10",
  "cgbgdb": "2026-05-20",
  "cggfon": "2026-05-10",
  "cgkmfo": "2026-05-20",
  "cglbbp": "2026-05-20",
  "cglbkh": "2026-05-20",
  "cglhbc": "2026-05-20",
  "cglhgj": "2026-05-20",
  "cglhpb": "2026-05-20",
  "cglixb": "2026-05-17",
  "chefc": "2026-05-13",
  "chexm": "2026-05-20",
  "chngm": "2026-05-10",
  "cibpj": "2026-05-18",
  "cjned": "2026-05-12",
  "cjofm": "2026-05-20",
  "ckejf": "2026-05-20",
  "ckifi": "2026-05-16",
  "ckmbi": "2026-05-10",
  "clobh": "2026-05-12",
  "cobhl": "2026-05-15",
  "cpfjn": "2026-05-19",
  "cxbfl": "2026-05-20",
  "cxcdc": "2026-05-20",
  "cxjgi": "2026-05-15",
  "cxpfl": "2026-05-10",
  "cxxmm": "2026-05-20",
  "dbgix": "2026-05-20",
  "dbkkg": "2026-05-20",
  "dckbm": "2026-05-16",
  "ddlfl": "2026-05-10",
  "ddpbk": "2026-05-17",
  "debde": "2026-05-13",
  "defgl": "2026-05-18",
  "dehhn": "2026-05-14",
  "deoxm": "2026-05-13",
  "dexcd": "2026-05-20",
  "dfccd": "2026-05-12",
  "dfkid": "2026-05-20",
  "dgkpi": "2026-05-20",
  "dgogm": "2026-05-20",
  "dhndi": "2026-05-20",
  "djfom": "2026-05-20",
  "dkcml": "2026-05-19",
  "dkgmd": "2026-05-20",
  "dldci": "2026-05-20",
  "dlgep": "2026-05-10",
  "dmjbf": "2026-05-20",
  "dmpix": "2026-05-17",
  "docmi": "2026-05-20",
  "domkp": "2026-05-14",
  "dxhin": "2026-05-15",
  "ebblm": "2026-05-11",
  "ebogf": "2026-05-20",
  "ebpox": "2026-05-20",
  "efgxo": "2026-05-16",
  "efhnd": "2026-05-20",
  "efkdd": "2026-05-20",
  "egdlf": "2026-05-19",
  "ehdbp": "2026-05-20",
  "ehokg": "2026-05-19",
  "ejxkc": "2026-05-20",
  "eklkn": "2026-05-20",
  "elbeg": "2026-05-14",
  "elbhk": "2026-05-10",
  "elell": "2026-05-20",
  "ellnd": "2026-05-20",
  "elmcd": "2026-05-20",
  "emfxk": "2026-05-20",
  "engdc": "2026-05-13",
  "enpmx": "2026-05-20",
  "eobfd": "2026-05-17",
  "eopgc": "2026-05-20",
  "epbbf": "2026-05-20",
  "epdim": "2026-05-12",
  "exxbi": "2026-05-13",
  "fbkmo": "2026-05-19",
  "fcdmk": "2026-05-15",
  "fdfpp": "2026-05-20",
  "fdgpd": "2026-05-20",
  "fdlde": "2026-05-15",
  "fehkc": "2026-05-10",
  "ffbxf": "2026-05-20",
  "ffgec": "2026-05-19",
  "ffjjl": "2026-05-20",
  "ffnje": "2026-05-16",
  "ffolg": "2026-05-10",
  "ffomg": "2026-05-20",
  "fgbmo": "2026-05-19",
  "fgbnm": "2026-05-20",
  "fgdln": "2026-05-20",
  "fgide": "2026-05-19",
  "fhhnh": "2026-05-13",
  "fhmnc": "2026-05-20",
  "ficoh": "2026-05-14",
  "fidhi": "2026-05-20",
  "fiokh": "2026-05-10",
  "fixch": "2026-05-20",
  "fjcck": "2026-05-20",
  "fjfge": "2026-05-14",
  "fkjho": "2026-05-20",
  "fldob": "2026-05-16",
  "flfon": "2026-05-20",
  "flpil": "2026-05-20",
  "fmgxk": "2026-05-10",
  "fnbpc": "2026-05-20",
  "fnplk": "2026-05-10",
  "fobeg": "2026-05-19",
  "foklh": "2026-05-12",
  "fopcd": "2026-05-20",
  "fxlkk": "2026-05-15",
  "gbikf": "2026-05-12",
  "gbipk": "2026-05-10",
  "gcxdf": "2026-05-10",
  "gdhde": "2026-05-20",
  "gfoog": "2026-05-10",
  "ggbon": "2026-05-17",
  "ggobl": "2026-05-10",
  "ghbjk": "2026-05-18",
  "ghgnl": "2026-05-20",
  "ginpb": "2026-05-18",
  "giodb": "2026-05-20",
  "gjmnk": "2026-05-17",
  "gkbjf": "2026-05-18",
  "gkifd": "2026-05-18",
  "glpmi": "2026-05-12",
  "gmcmk": "2026-05-17",
  "gmdfi": "2026-05-18",
  "gmgbh": "2026-05-11",
  "gmlmx": "2026-05-20",
  "gmpio": "2026-05-10",
  "gnjnp": "2026-05-18",
  "gnlgm": "2026-05-10",
  "gphoc": "2026-05-12",
  "gppij": "2026-05-20",
  "gxfpx": "2026-05-10",
  "gxkdx": "2026-05-20",
  "gxphc": "2026-05-20",
  "hbjho": "2026-05-20",
  "hcjge": "2026-05-20",
  "hcoof": "2026-05-19",
  "hcpmf": "2026-05-19",
  "hdbpj": "2026-05-20",
  "hdkib": "2026-05-11",
  "hdkpk": "2026-05-20",
  "hdlbp": "2026-05-10",
  "hdolk": "2026-05-20",
  "hggml": "2026-05-16",
  "hgkgj": "2026-05-20",
  "hhidj": "2026-05-13",
  "hibbg": "2026-05-18",
  "hibfb": "2026-05-20",
  "hieex": "2026-05-20",
  "hkxhl": "2026-05-20",
  "hopie": "2026-05-13",
  "jnkkp": "2026-05-20",
  "kxldd": "2026-05-20",
  "lbfco": "2026-05-20",
  "lijef": "2026-05-20",
  "njfne": "2026-05-19",
  "nxell": "2026-05-20",
  "obgkh": "2026-05-20",
  "oeddm": "2026-05-16",
  "ondgp": "2026-05-15"
}
